COPYING.LESSER.txt
COPYING.txt
LICENSE.txt
MANIFEST.in
setup.py
fuzzylib/__init__.py
fuzzylib/fis.py
fuzzylib/linguisticvar.py
fuzzylib/membership.py
fuzzylib/rule.py
fuzzylib/ruleparser.py
fuzzylib.egg-info/PKG-INFO
fuzzylib.egg-info/SOURCES.txt
fuzzylib.egg-info/dependency_links.txt
fuzzylib.egg-info/top_level.txt