Metadata-Version: 1.0
Name: fuzzylib
Version: 0.1.1
Summary: Fuzzy inference system library
Home-page: http://www.pythonhosted.org/fuzzylib
Author: Leandro Mattioli
Author-email: leandro.mattioli@gmail.com
License: GPL
Keywords: fuzzy
Platform: UNKNOWN
